ai_soulmate_sketch_filter/__init__.py
ai_soulmate_sketch_filter-1768297.341.138.dist-info/licenses/LICENSE
ai_soulmate_sketch_filter-1768297.341.138.dist-info/METADATA
ai_soulmate_sketch_filter-1768297.341.138.dist-info/WHEEL
ai_soulmate_sketch_filter-1768297.341.138.dist-info/top_level.txt
ai_soulmate_sketch_filter-1768297.341.138.dist-info/RECORD
