Metadata-Version: 2.4
Name: ai-soulmate-sketch-filter
Version: 1768297.341.138
Summary: High-quality integration for https://supermaker.ai/image/blog/ai-soulmate-drawing-free-tool-generate-your-soulmate-sketch/
Home-page: https://supermaker.ai/image/blog/ai-soulmate-drawing-free-tool-generate-your-soulmate-sketch/
Author: SuperMaker
Classifier: Programming Language :: Python :: 3
Classifier: License :: OSI Approved :: MIT License
Requires-Python: >=3.6
License-File: LICENSE
Dynamic: author
Dynamic: classifier
Dynamic: description
Dynamic: description-content-type
Dynamic: home-page
Dynamic: license-file
Dynamic: requires-python
Dynamic: summary
